yany/__init__.py
yany/app.py
yany/cmds/__init__.py
yany/cmds/generate_base.py
yany/cmds/generate_init.py
yany/cmds/generate_prompt.py
yany/cmds/generate_qa.py
yany/templates/attribute.json
yany/templates/env
yany/templates/helper.py
yany/templates/renshe_1000.jsonl
yany-0.3.0.dist-info/LICENSE
yany-0.3.0.dist-info/METADATA
yany-0.3.0.dist-info/WHEEL
yany-0.3.0.dist-info/entry_points.txt
yany-0.3.0.dist-info/top_level.txt
yany-0.3.0.dist-info/RECORD
