Metadata-Version: 2.1
Name: yany
Version: 0.3.0
Summary: 星火人设定制工具
Author-email: MJ <tywf91@gmail.com>
License: MIT
Project-URL: homepage, https://github.com/mjason/yany.git
Project-URL: documentation, https://github.com/mjason/yany.git
Project-URL: source, https://github.com/mjason/yany.git
Project-URL: tracker, https://github.com/mjason/yany.git
Classifier: Programming Language :: Python :: 3
Classifier: License :: OSI Approved :: MIT License
Classifier: Operating System :: OS Independent
License-File: LICENSE
Requires-Dist: openai ~=1.13.3
Requires-Dist: python-dotenv ~=1.0.0
Requires-Dist: pandas ~=2.2.0
Requires-Dist: openpyxl ~=3.1.0
Provides-Extra: dev
Requires-Dist: pytest >=6.0 ; extra == 'dev'
Requires-Dist: flake8 >=3.8 ; extra == 'dev'
